{
    "initial state": "pp",
    "order": "NNLOapprox+NNLL",
    "source": "hepi-0.2.6.4+dirty",
    "contact": "Alexander Puck Neuwirth <alexander@neuwirth-informatik.de>",
    "tool": "Resummino-resummino 3.1.1-dev",
    "process_latex": "$\\tilde{\\chi}_{2}^{0}\\tilde{\\chi}_{1}^{+}$",
    "comment": "0.0.0",
    "reference": "?",
    "Ecom [GeV]": "13000",
    "process_id": "pp_13000_1000023_1000024",
    "PDF set": "PDF4LHC21_40",
    "parameters": [
        [
            "MASS_1000022"
        ],
        [
            "MASS_1000024"
        ]
    ],
    "data": {
        "80.0": {
            "80.75": {
                "xsec_pb": 7.7647615,
                "unc_up_pb": 0.2901875631195878,
                "unc_down_pb": -0.35421883743629934,
                "unc_scale_up_pb": 0.1936750000000007,
                "unc_scale_down_pb": -0.28066379999999924,
                "unc_pdf_up_pb": 0.21609908876319728,
                "unc_pdf_down_pb": -0.21609908876319728
            },
            "81.0": {
                "xsec_pb": 7.6296216,
                "unc_up_pb": 0.2853349873112021,
                "unc_down_pb": -0.34755637100655234,
                "unc_scale_up_pb": 0.18972950000000033,
                "unc_scale_down_pb": -0.2745481000000005,
                "unc_pdf_up_pb": 0.21311680321747,
                "unc_pdf_down_pb": -0.21311680321747
            },
            "81.5": {
                "xsec_pb": 7.367632,
                "unc_up_pb": 0.27483310181193965,
                "unc_down_pb": -0.33243023629077784,
                "unc_scale_up_pb": 0.18163579999999868,
                "unc_scale_down_pb": -0.2607071000000012,
                "unc_pdf_up_pb": 0.20625632113933431,
                "unc_pdf_down_pb": -0.20625632113933431
            },
            "82.5": {
                "xsec_pb": 6.8816551,
                "unc_up_pb": 0.25358166050122566,
                "unc_down_pb": -0.3077489440566107,
                "unc_scale_up_pb": 0.16453339999999983,
                "unc_scale_down_pb": -0.2397436000000006,
                "unc_pdf_up_pb": 0.19295703881174897,
                "unc_pdf_down_pb": -0.19295703881174897
            },
            "85.0": {
                "xsec_pb": 5.8367795,
                "unc_up_pb": 0.2133344273527895,
                "unc_down_pb": -0.2543042082820348,
                "unc_scale_up_pb": 0.13358680000000112,
                "unc_scale_down_pb": -0.19236549999999886,
                "unc_pdf_up_pb": 0.16633143046250345,
                "unc_pdf_down_pb": -0.16633143046250345
            },
            "87.5": {
                "xsec_pb": 4.9933434,
                "unc_up_pb": 0.1806520291316196,
                "unc_down_pb": -0.21291236331526475,
                "unc_scale_up_pb": 0.10919970000000045,
                "unc_scale_down_pb": -0.15691109999999941,
                "unc_pdf_up_pb": 0.14391171303713068,
                "unc_pdf_down_pb": -0.14391171303713068
            },
            "90.0": {
                "xsec_pb": 4.3034068,
                "unc_up_pb": 0.15455949235800912,
                "unc_down_pb": -0.1795384811829643,
                "unc_scale_up_pb": 0.09092429999999974,
                "unc_scale_down_pb": -0.1288901,
                "unc_pdf_up_pb": 0.1249856325642094,
                "unc_pdf_down_pb": -0.1249856325642094
            },
            "95.0": {
                "xsec_pb": 3.2598041,
                "unc_up_pb": 0.11590393212094524,
                "unc_down_pb": -0.13144990404167883,
                "unc_scale_up_pb": 0.06331469999999961,
                "unc_scale_down_pb": -0.08862340000000057,
                "unc_pdf_up_pb": 0.0970822859486045,
                "unc_pdf_down_pb": -0.0970822859486045
            },
            "100.0": {
                "xsec_pb": 2.5228881,
                "unc_up_pb": 0.08923983959344212,
                "unc_down_pb": -0.09843779990264528,
                "unc_scale_up_pb": 0.04603180000000018,
                "unc_scale_down_pb": -0.06200949999999983,
                "unc_pdf_up_pb": 0.07645143791599512,
                "unc_pdf_down_pb": -0.07645143791599512
            },
            "110.0": {
                "xsec_pb": 1.5916387,
                "unc_up_pb": 0.056361156929001205,
                "unc_down_pb": -0.06042199773795562,
                "unc_scale_up_pb": 0.02516929999999995,
                "unc_scale_down_pb": -0.03328260000000016,
                "unc_pdf_up_pb": 0.05042902287260287,
                "unc_pdf_down_pb": -0.05042902287260287
            }
        },
        "60.0": {
            "80.0": {
                "xsec_pb": 5.2062873,
                "unc_up_pb": 0.18891701132752228,
                "unc_down_pb": -0.22334699550628148,
                "unc_scale_up_pb": 0.11614899999999961,
                "unc_scale_down_pb": -0.16638759999999975,
                "unc_pdf_up_pb": 0.14899344605694292,
                "unc_pdf_down_pb": -0.14899344605694292
            },
            "90.0": {
                "xsec_pb": 2.9502292,
                "unc_up_pb": 0.10458441972912508,
                "unc_down_pb": -0.11735505870344004,
                "unc_scale_up_pb": 0.05605480000000007,
                "unc_scale_down_pb": -0.07730749999999986,
                "unc_pdf_up_pb": 0.08829360252610513,
                "unc_pdf_down_pb": -0.08829360252610513
            }
        },
        "100.0": {
            "100.75": {
                "xsec_pb": 3.4380628,
                "unc_up_pb": 0.12245447825721201,
                "unc_down_pb": -0.13944885354295977,
                "unc_scale_up_pb": 0.06765230000000044,
                "unc_scale_down_pb": -0.09501429999999966,
                "unc_pdf_up_pb": 0.10206990521184944,
                "unc_pdf_down_pb": -0.10206990521184944
            },
            "101.0": {
                "xsec_pb": 3.3924538,
                "unc_up_pb": 0.12038930869301895,
                "unc_down_pb": -0.13697354783308752,
                "unc_scale_up_pb": 0.06659219999999944,
                "unc_scale_down_pb": -0.0932882000000006,
                "unc_pdf_up_pb": 0.10029488793923175,
                "unc_pdf_down_pb": -0.10029488793923175
            },
            "101.5": {
                "xsec_pb": 3.3034777,
                "unc_up_pb": 0.1168941267825527,
                "unc_down_pb": -0.13300198293862217,
                "unc_scale_up_pb": 0.06417869999999959,
                "unc_scale_down_pb": -0.09024520000000025,
                "unc_pdf_up_pb": 0.09770021157891898,
                "unc_pdf_down_pb": -0.09770021157891898
            },
            "102.5": {
                "xsec_pb": 3.1341433,
                "unc_up_pb": 0.11168658746998718,
                "unc_down_pb": -0.12593158069674637,
                "unc_scale_up_pb": 0.060513999999999735,
                "unc_scale_down_pb": -0.08394530000000011,
                "unc_pdf_up_pb": 0.09387198530281082,
                "unc_pdf_down_pb": -0.09387198530281082
            },
            "105.0": {
                "xsec_pb": 2.7572669,
                "unc_up_pb": 0.09839329871702256,
                "unc_down_pb": -0.10913027817639447,
                "unc_scale_up_pb": 0.05160000000000009,
                "unc_scale_down_pb": -0.06993379999999982,
                "unc_pdf_up_pb": 0.08377756998395956,
                "unc_pdf_down_pb": -0.08377756998395956
            },
            "107.5": {
                "xsec_pb": 2.4376064,
                "unc_up_pb": 0.08723146411539406,
                "unc_down_pb": -0.09583027320693283,
                "unc_scale_up_pb": 0.04395419999999994,
                "unc_scale_down_pb": -0.05921220000000016,
                "unc_pdf_up_pb": 0.07534823577281241,
                "unc_pdf_down_pb": -0.07534823577281241
            },
            "110.0": {
                "xsec_pb": 2.1638845,
                "unc_up_pb": 0.07678197506346066,
                "unc_down_pb": -0.08409455633419952,
                "unc_scale_up_pb": 0.03739870000000045,
                "unc_scale_down_pb": -0.05074529999999977,
                "unc_pdf_up_pb": 0.06705825029745309,
                "unc_pdf_down_pb": -0.06705825029745309
            },
            "115.0": {
                "xsec_pb": 1.7257922,
                "unc_up_pb": 0.061283240128094746,
                "unc_down_pb": -0.06625879959286743,
                "unc_scale_up_pb": 0.027645599999999937,
                "unc_scale_down_pb": -0.037401499999999976,
                "unc_pdf_up_pb": 0.05469329320161428,
                "unc_pdf_down_pb": -0.05469329320161428
            },
            "120.0": {
                "xsec_pb": 1.3951506,
                "unc_up_pb": 0.04941934853731088,
                "unc_down_pb": -0.05268763192042501,
                "unc_scale_up_pb": 0.020924400000000065,
                "unc_scale_down_pb": -0.027776699999999876,
                "unc_pdf_up_pb": 0.04477098942945311,
                "unc_pdf_down_pb": -0.04477098942945311
            },
            "130.0": {
                "xsec_pb": 0.94387057,
                "unc_up_pb": 0.0338471190840626,
                "unc_down_pb": -0.03539052755937269,
                "unc_scale_up_pb": 0.012606229999999996,
                "unc_scale_down_pb": -0.016302729999999988,
                "unc_pdf_up_pb": 0.031411947336607716,
                "unc_pdf_down_pb": -0.031411947336607716
            }
        },
        "125.0": {
            "125.75": {
                "xsec_pb": 1.5608734,
                "unc_up_pb": 0.0552939156248233,
                "unc_down_pb": -0.05916917959406784,
                "unc_scale_up_pb": 0.02446270000000006,
                "unc_scale_down_pb": -0.03227999999999975,
                "unc_pdf_up_pb": 0.04958823866437557,
                "unc_pdf_down_pb": -0.04958823866437557
            },
            "126.0": {
                "xsec_pb": 1.5445091,
                "unc_up_pb": 0.05463739877700026,
                "unc_down_pb": -0.05839968883784365,
                "unc_scale_up_pb": 0.024178000000000144,
                "unc_scale_down_pb": -0.03177819999999987,
                "unc_pdf_up_pb": 0.04899662907912089,
                "unc_pdf_down_pb": -0.04899662907912089
            },
            "126.5": {
                "xsec_pb": 1.5124888,
                "unc_up_pb": 0.053597176012226036,
                "unc_down_pb": -0.05735098918532745,
                "unc_scale_up_pb": 0.02339380000000002,
                "unc_scale_down_pb": -0.031044300000000025,
                "unc_pdf_up_pb": 0.0482222707682409,
                "unc_pdf_down_pb": -0.0482222707682409
            },
            "127.5": {
                "xsec_pb": 1.4507819,
                "unc_up_pb": 0.051471454335666245,
                "unc_down_pb": -0.054809926992001934,
                "unc_scale_up_pb": 0.02210409999999996,
                "unc_scale_down_pb": -0.029041499999999942,
                "unc_pdf_up_pb": 0.04648353874887949,
                "unc_pdf_down_pb": -0.04648353874887949
            },
            "130.0": {
                "xsec_pb": 1.310274,
                "unc_up_pb": 0.04669731654703799,
                "unc_down_pb": -0.04959434905122037,
                "unc_scale_up_pb": 0.019324300000000072,
                "unc_scale_down_pb": -0.025541899999999895,
                "unc_pdf_up_pb": 0.042511302052563336,
                "unc_pdf_down_pb": -0.042511302052563336
            },
            "132.5": {
                "xsec_pb": 1.1865048,
                "unc_up_pb": 0.04236022112922866,
                "unc_down_pb": -0.04464945545812604,
                "unc_scale_up_pb": 0.017007899999999854,
                "unc_scale_down_pb": -0.02210100000000015,
                "unc_pdf_up_pb": 0.03879587183847226,
                "unc_pdf_down_pb": -0.03879587183847226
            },
            "135.0": {
                "xsec_pb": 1.0773183,
                "unc_up_pb": 0.03842522868011332,
                "unc_down_pb": -0.04046683850857412,
                "unc_scale_up_pb": 0.014870499999999898,
                "unc_scale_down_pb": -0.01954990000000001,
                "unc_pdf_up_pb": 0.03543115054396359,
                "unc_pdf_down_pb": -0.03543115054396359
            },
            "140.0": {
                "xsec_pb": 0.89450919,
                "unc_up_pb": 0.03230754878437157,
                "unc_down_pb": -0.03366794407766614,
                "unc_scale_up_pb": 0.011839490000000119,
                "unc_scale_down_pb": -0.015163319999999925,
                "unc_pdf_up_pb": 0.030060009730445047,
                "unc_pdf_down_pb": -0.030060009730445047
            },
            "145.0": {
                "xsec_pb": 0.74940574,
                "unc_up_pb": 0.027406446154671263,
                "unc_down_pb": -0.0284537319704148,
                "unc_scale_up_pb": 0.009206359999999858,
                "unc_scale_down_pb": -0.011969070000000137,
                "unc_pdf_up_pb": 0.02581387662439139,
                "unc_pdf_down_pb": -0.02581387662439139
            },
            "155.0": {
                "xsec_pb": 0.53793204,
                "unc_up_pb": 0.02004537679379451,
                "unc_down_pb": -0.020585494754637144,
                "unc_scale_up_pb": 0.006010740000000014,
                "unc_scale_down_pb": -0.007620659999999946,
                "unc_pdf_up_pb": 0.01912297402230089,
                "unc_pdf_down_pb": -0.01912297402230089
            }
        },
        "150.0": {
            "151.0": {
                "xsec_pb": 0.81538046,
                "unc_up_pb": 0.02955141244751809,
                "unc_down_pb": -0.030722972190808953,
                "unc_scale_up_pb": 0.01043368999999994,
                "unc_scale_down_pb": -0.013396900000000045,
                "unc_pdf_up_pb": 0.027648220388068814,
                "unc_pdf_down_pb": -0.027648220388068814
            },
            "151.5": {
                "xsec_pb": 0.80126434,
                "unc_up_pb": 0.02915329847734658,
                "unc_down_pb": -0.03030389629160666,
                "unc_scale_up_pb": 0.010163330000000026,
                "unc_scale_down_pb": -0.013103610000000043,
                "unc_pdf_up_pb": 0.02732437621283155,
                "unc_pdf_down_pb": -0.02732437621283155
            },
            "152.5": {
                "xsec_pb": 0.77391717,
                "unc_up_pb": 0.028184212925393273,
                "unc_down_pb": -0.029304664489679912,
                "unc_scale_up_pb": 0.009620189999999973,
                "unc_scale_down_pb": -0.01252842999999998,
                "unc_pdf_up_pb": 0.026491542095314242,
                "unc_pdf_down_pb": -0.026491542095314242
            },
            "155.0": {
                "xsec_pb": 0.71035747,
                "unc_up_pb": 0.026159202539719026,
                "unc_down_pb": -0.027078060545543833,
                "unc_scale_up_pb": 0.008600899999999911,
                "unc_scale_down_pb": -0.011085710000000026,
                "unc_pdf_up_pb": 0.024704825372870796,
                "unc_pdf_down_pb": -0.024704825372870796
            },
            "157.5": {
                "xsec_pb": 0.6532082,
                "unc_up_pb": 0.02405887438631457,
                "unc_down_pb": -0.024826497322879754,
                "unc_scale_up_pb": 0.007781719999999881,
                "unc_scale_down_pb": -0.009903570000000084,
                "unc_pdf_up_pb": 0.022765637934792422,
                "unc_pdf_down_pb": -0.022765637934792422
            },
            "160.0": {
                "xsec_pb": 0.60175395,
                "unc_up_pb": 0.022309331980845205,
                "unc_down_pb": -0.022950196418755543,
                "unc_scale_up_pb": 0.006981650000000117,
                "unc_scale_down_pb": -0.008817519999999968,
                "unc_pdf_up_pb": 0.021188743632151973,
                "unc_pdf_down_pb": -0.021188743632151973
            },
            "165.0": {
                "xsec_pb": 0.51320864,
                "unc_up_pb": 0.019245139183744993,
                "unc_down_pb": -0.01973403094809873,
                "unc_scale_up_pb": 0.005666059999999973,
                "unc_scale_down_pb": -0.007152680000000078,
                "unc_pdf_up_pb": 0.018392149039144864,
                "unc_pdf_down_pb": -0.018392149039144864
            },
            "170.0": {
                "xsec_pb": 0.44038489,
                "unc_up_pb": 0.01676040644167566,
                "unc_down_pb": -0.0170937346185719,
                "unc_scale_up_pb": 0.004652460000000053,
                "unc_scale_down_pb": -0.005738459999999973,
                "unc_pdf_up_pb": 0.016101734069303316,
                "unc_pdf_down_pb": -0.016101734069303316
            },
            "180.0": {
                "xsec_pb": 0.32957486,
                "unc_up_pb": 0.012892203683144286,
                "unc_down_pb": -0.013076561111400018,
                "unc_scale_up_pb": 0.0031709000000000043,
                "unc_scale_down_pb": -0.0038525499999999824,
                "unc_pdf_up_pb": 0.012496171773694501,
                "unc_pdf_down_pb": -0.012496171773694501
            }
        },
        "175.0": {
            "176.5": {
                "xsec_pb": 0.46651283,
                "unc_up_pb": 0.017588776201398,
                "unc_down_pb": -0.017974791361962023,
                "unc_scale_up_pb": 0.004977730000000041,
                "unc_scale_down_pb": -0.006205309999999936,
                "unc_pdf_up_pb": 0.016869714055370494,
                "unc_pdf_down_pb": -0.016869714055370494
            },
            "177.5": {
                "xsec_pb": 0.45267264,
                "unc_up_pb": 0.0171584457697398,
                "unc_down_pb": -0.01754856916684667,
                "unc_scale_up_pb": 0.004799959999999992,
                "unc_scale_down_pb": -0.0060481099999999954,
                "unc_pdf_up_pb": 0.016473392037813638,
                "unc_pdf_down_pb": -0.016473392037813638
            },
            "180.0": {
                "xsec_pb": 0.4201521,
                "unc_up_pb": 0.01616007103888607,
                "unc_down_pb": -0.01643191731221717,
                "unc_scale_up_pb": 0.00442128,
                "unc_scale_down_pb": -0.005329889999999976,
                "unc_pdf_up_pb": 0.015543493144832131,
                "unc_pdf_down_pb": -0.015543493144832131
            },
            "182.5": {
                "xsec_pb": 0.39053526,
                "unc_up_pb": 0.015006505412002245,
                "unc_down_pb": -0.015263182922442917,
                "unc_scale_up_pb": 0.003964330000000016,
                "unc_scale_down_pb": -0.004846179999999978,
                "unc_pdf_up_pb": 0.014473399473916033,
                "unc_pdf_down_pb": -0.014473399473916033
            },
            "185.0": {
                "xsec_pb": 0.36346032,
                "unc_up_pb": 0.01413245456309651,
                "unc_down_pb": -0.014343720212789603,
                "unc_scale_up_pb": 0.003640140000000014,
                "unc_scale_down_pb": -0.004389379999999998,
                "unc_pdf_up_pb": 0.013655608838802761,
                "unc_pdf_down_pb": -0.013655608838802761
            }
        },
        "200.0": {
            "201.0": {
                "xsec_pb": 0.29431553,
                "unc_up_pb": 0.011628537350447464,
                "unc_down_pb": -0.011775850086547933,
                "unc_scale_up_pb": 0.002744179999999985,
                "unc_scale_down_pb": -0.0033133499999999927,
                "unc_pdf_up_pb": 0.011300104293251076,
                "unc_pdf_down_pb": -0.011300104293251076
            },
            "201.5": {
                "xsec_pb": 0.29039092,
                "unc_up_pb": 0.011483528985188327,
                "unc_down_pb": -0.01162428413486448,
                "unc_scale_up_pb": 0.0027197500000000208,
                "unc_scale_down_pb": -0.0032633699999999877,
                "unc_pdf_up_pb": 0.011156809485294676,
                "unc_pdf_down_pb": -0.011156809485294676
            },
            "202.5": {
                "xsec_pb": 0.2827504,
                "unc_up_pb": 0.011232158520467212,
                "unc_down_pb": -0.01137700450911427,
                "unc_scale_up_pb": 0.00258296999999999,
                "unc_scale_down_pb": -0.0031538200000000016,
                "unc_pdf_up_pb": 0.010931132192412884,
                "unc_pdf_down_pb": -0.010931132192412884
            },
            "205.0": {
                "xsec_pb": 0.26464136,
                "unc_up_pb": 0.01057250194593564,
                "unc_down_pb": -0.010688424733304357,
                "unc_scale_up_pb": 0.002391630000000061,
                "unc_scale_down_pb": -0.0028608599999999373,
                "unc_pdf_up_pb": 0.010298441791839804,
                "unc_pdf_down_pb": -0.010298441791839804
            },
            "207.5": {
                "xsec_pb": 0.24795972,
                "unc_up_pb": 0.00998773694392096,
                "unc_down_pb": -0.010089721110479836,
                "unc_scale_up_pb": 0.0021857900000000208,
                "unc_scale_down_pb": -0.002612520000000007,
                "unc_pdf_up_pb": 0.009745625240940827,
                "unc_pdf_down_pb": -0.009745625240940827
            },
            "210.0": {
                "xsec_pb": 0.23254911,
                "unc_up_pb": 0.009446203959487308,
                "unc_down_pb": -0.0095328579443803,
                "unc_scale_up_pb": 0.002020189999999991,
                "unc_scale_down_pb": -0.0023928600000000105,
                "unc_pdf_up_pb": 0.009227654176882342,
                "unc_pdf_down_pb": -0.009227654176882342
            },
            "215.0": {
                "xsec_pb": 0.20513394,
                "unc_up_pb": 0.00845316658551991,
                "unc_down_pb": -0.008524223950451425,
                "unc_scale_up_pb": 0.0017088999999999993,
                "unc_scale_down_pb": -0.002031429999999987,
                "unc_pdf_up_pb": 0.008278628274814013,
                "unc_pdf_down_pb": -0.008278628274814013
            },
            "220.0": {
                "xsec_pb": 0.18157521,
                "unc_up_pb": 0.007627107677747139,
                "unc_down_pb": -0.007682163482375862,
                "unc_scale_up_pb": 0.0014571600000000129,
                "unc_scale_down_pb": -0.0017222599999999755,
                "unc_pdf_up_pb": 0.007486618479817795,
                "unc_pdf_down_pb": -0.007486618479817795
            },
            "230.0": {
                "xsec_pb": 0.14362329,
                "unc_up_pb": 0.006191690006242972,
                "unc_down_pb": -0.00621915491900698,
                "unc_scale_up_pb": 0.0010797199999999924,
                "unc_scale_down_pb": -0.0012274599999999997,
                "unc_pdf_up_pb": 0.006096821291050683,
                "unc_pdf_down_pb": -0.006096821291050683
            }
        },
        "225.0": {
            "227.5": {
                "xsec_pb": 0.18552921,
                "unc_up_pb": 0.007765433394418967,
                "unc_down_pb": -0.007818218940120395,
                "unc_scale_up_pb": 0.0014996600000000138,
                "unc_scale_down_pb": -0.0017525899999999983,
                "unc_pdf_up_pb": 0.007619250336322942,
                "unc_pdf_down_pb": -0.007619250336322942
            },
            "230.0": {
                "xsec_pb": 0.174762,
                "unc_up_pb": 0.007351149179184792,
                "unc_down_pb": -0.007393897224639358,
                "unc_scale_up_pb": 0.001395690000000005,
                "unc_scale_down_pb": -0.0016056999999999877,
                "unc_pdf_up_pb": 0.007217440244195268,
                "unc_pdf_down_pb": -0.007217440244195268
            },
            "232.5": {
                "xsec_pb": 0.16475463,
                "unc_up_pb": 0.0069798902801824145,
                "unc_down_pb": -0.007019865553768427,
                "unc_scale_up_pb": 0.001279269999999999,
                "unc_scale_down_pb": -0.0014819500000000096,
                "unc_pdf_up_pb": 0.006861656985778632,
                "unc_pdf_down_pb": -0.006861656985778632
            }
        },
        "250.0": {
            "251.0": {
                "xsec_pb": 0.13076196,
                "unc_up_pb": 0.005702828639989723,
                "unc_down_pb": -0.005722693801024749,
                "unc_scale_up_pb": 0.0009513699999999931,
                "unc_scale_down_pb": -0.0010639900000000008,
                "unc_pdf_up_pb": 0.005622912912377984,
                "unc_pdf_down_pb": -0.005622912912377984
            },
            "251.5": {
                "xsec_pb": 0.12932271,
                "unc_up_pb": 0.005648801564344228,
                "unc_down_pb": -0.005667589135120674,
                "unc_scale_up_pb": 0.0009388199999999791,
                "unc_scale_down_pb": -0.0010459399999999952,
                "unc_pdf_up_pb": 0.00557024022111595,
                "unc_pdf_down_pb": -0.00557024022111595
            },
            "252.5": {
                "xsec_pb": 0.12650126,
                "unc_up_pb": 0.005539850921680757,
                "unc_down_pb": -0.005557821364720784,
                "unc_scale_up_pb": 0.0009098200000000056,
                "unc_scale_down_pb": -0.0010135099999999952,
                "unc_pdf_up_pb": 0.005464629521023998,
                "unc_pdf_down_pb": -0.005464629521023998
            },
            "255.0": {
                "xsec_pb": 0.11976907,
                "unc_up_pb": 0.005280975300919642,
                "unc_down_pb": -0.005296699651936408,
                "unc_scale_up_pb": 0.0008388099999999954,
                "unc_scale_down_pb": -0.0009327000000000085,
                "unc_pdf_up_pb": 0.005213933056035845,
                "unc_pdf_down_pb": -0.005213933056035845
            },
            "257.5": {
                "xsec_pb": 0.1134672,
                "unc_up_pb": 0.00504347358660542,
                "unc_down_pb": -0.005058175865466388,
                "unc_scale_up_pb": 0.0007808699999999891,
                "unc_scale_down_pb": -0.0008707900000000102,
                "unc_pdf_up_pb": 0.0049826567072081725,
                "unc_pdf_down_pb": -0.0049826567072081725
            },
            "260.0": {
                "xsec_pb": 0.10756226,
                "unc_up_pb": 0.0048171949054501804,
                "unc_down_pb": -0.0048291731615873155,
                "unc_scale_up_pb": 0.0007333499999999937,
                "unc_scale_down_pb": -0.0008083000000000118,
                "unc_pdf_up_pb": 0.004761046579754833,
                "unc_pdf_down_pb": -0.004761046579754833
            },
            "265.0": {
                "xsec_pb": 0.096840902,
                "unc_up_pb": 0.004386887374205357,
                "unc_down_pb": -0.004398206336337852,
                "unc_scale_up_pb": 0.0006328539999999883,
                "unc_scale_down_pb": -0.0007070660000000062,
                "unc_pdf_up_pb": 0.0043409994988074345,
                "unc_pdf_down_pb": -0.0043409994988074345
            },
            "270.0": {
                "xsec_pb": 0.087374887,
                "unc_up_pb": 0.004022830162578762,
                "unc_down_pb": -0.00402942692717831,
                "unc_scale_up_pb": 0.0005628720000000198,
                "unc_scale_down_pb": -0.0006082299999999874,
                "unc_pdf_up_pb": 0.003983257163248382,
                "unc_pdf_down_pb": -0.003983257163248382
            },
            "280.0": {
                "xsec_pb": 0.071588204,
                "unc_up_pb": 0.0033931091729166884,
                "unc_down_pb": -0.0033963205735588775,
                "unc_scale_up_pb": 0.00044266899999999276,
                "unc_scale_down_pb": -0.0004666470000000006,
                "unc_pdf_up_pb": 0.003364109691399842,
                "unc_pdf_down_pb": -0.003364109691399842
            }
        },
        "300.0": {
            "301.0": {
                "xsec_pb": 0.066016462,
                "unc_up_pb": 0.0031581042149276045,
                "unc_down_pb": -0.0031597989068001603,
                "unc_scale_up_pb": 0.0004016670000000014,
                "unc_scale_down_pb": -0.0004147810000000099,
                "unc_pdf_up_pb": 0.003132456839839057,
                "unc_pdf_down_pb": -0.003132456839839057
            },
            "301.5": {
                "xsec_pb": 0.065390746,
                "unc_up_pb": 0.0031334319699459403,
                "unc_down_pb": -0.00313496447821395,
                "unc_scale_up_pb": 0.00039712899999999607,
                "unc_scale_down_pb": -0.00040904499999999677,
                "unc_pdf_up_pb": 0.0031081641635599434,
                "unc_pdf_down_pb": -0.0031081641635599434
            },
            "302.5": {
                "xsec_pb": 0.064160953,
                "unc_up_pb": 0.0030832890121519326,
                "unc_down_pb": -0.003084687707002429,
                "unc_scale_up_pb": 0.0003882749999999935,
                "unc_scale_down_pb": -0.0003992300000000004,
                "unc_pdf_up_pb": 0.0030587438037259465,
                "unc_pdf_down_pb": -0.0030587438037259465
            },
            "305.0": {
                "xsec_pb": 0.061207989,
                "unc_up_pb": 0.0029646639715091164,
                "unc_down_pb": -0.0029658654805168197,
                "unc_scale_up_pb": 0.0003675420000000089,
                "unc_scale_down_pb": -0.00037711099999999595,
                "unc_pdf_up_pb": 0.0029417928788750976,
                "unc_pdf_down_pb": -0.0029417928788750976
            },
            "307.5": {
                "xsec_pb": 0.058414669,
                "unc_up_pb": 0.0028439282368217388,
                "unc_down_pb": -0.00284482715627224,
                "unc_scale_up_pb": 0.00034777299999999914,
                "unc_scale_down_pb": -0.00035504899999999964,
                "unc_pdf_up_pb": 0.002822584233758667,
                "unc_pdf_down_pb": -0.002822584233758667
            },
            "310.0": {
                "xsec_pb": 0.055768654,
                "unc_up_pb": 0.002734821943469757,
                "unc_down_pb": -0.0027350600065116893,
                "unc_scale_up_pb": 0.0003288449999999943,
                "unc_scale_down_pb": -0.00033081900000000997,
                "unc_pdf_up_pb": 0.0027149791948482237,
                "unc_pdf_down_pb": -0.0027149791948482237
            }
        }
    }
}
