{
    "initial state": "pp",
    "order": "NNLOapprox+NNLL",
    "source": "hepi-0.2.17.12",
    "contact": "Alexander Puck Neuwirth <alexander@neuwirth-informatik.de>",
    "tool": "Resummino-resummino 3.1.2-dev",
    "process_latex": "$\\tilde{\\tau}_{1}^{-}\\overline{\\tilde{\\nu}}_{\\tau L}$",
    "comment": "0.0.0",
    "reference": "?",
    "Ecom [GeV]": "13600",
    "process_id": "pp_13600_1000015_-1000016",
    "PDF set": "PDF4LHC21_40",
    "parameters": [
        [
            "mass_1000015_-1000016"
        ]
    ],
    "data": {
        "50": {
            "xsec_pb": 4.848232,
            "unc_up_pb": 0.3787906123185216,
            "unc_down_pb": -0.3677280416826161,
            "unc_scale_up_pb": 0.35889539999999975,
            "unc_scale_down_pb": -0.3471995000000003,
            "unc_pdf_up_pb": 0.12114627455882074,
            "unc_pdf_down_pb": -0.12114627455882074
        },
        "60": {
            "xsec_pb": 2.0446003,
            "unc_up_pb": 0.15455264713569966,
            "unc_down_pb": -0.12765621612174644,
            "unc_scale_up_pb": 0.14519170000000003,
            "unc_scale_down_pb": -0.11614740000000023,
            "unc_pdf_up_pb": 0.052970661575649856,
            "unc_pdf_down_pb": -0.052970661575649856
        },
        "70": {
            "xsec_pb": 1.0747219,
            "unc_up_pb": 0.07849771767310751,
            "unc_down_pb": -0.06363832686240953,
            "unc_scale_up_pb": 0.07294600000000029,
            "unc_scale_down_pb": -0.05664859999999983,
            "unc_pdf_up_pb": 0.02899608187129557,
            "unc_pdf_down_pb": -0.02899608187129557
        },
        "80": {
            "xsec_pb": 0.63357186,
            "unc_up_pb": 0.045179451714252084,
            "unc_down_pb": -0.036972962136372356,
            "unc_scale_up_pb": 0.041512620000000056,
            "unc_scale_down_pb": -0.03239003999999995,
            "unc_pdf_up_pb": 0.017829336441270844,
            "unc_pdf_down_pb": -0.017829336441270844
        },
        "90": {
            "xsec_pb": 0.40220567,
            "unc_up_pb": 0.028163679479021222,
            "unc_down_pb": -0.023165528022869322,
            "unc_scale_up_pb": 0.025593939999999926,
            "unc_scale_down_pb": -0.019962430000000086,
            "unc_pdf_up_pb": 0.011753428311494578,
            "unc_pdf_down_pb": -0.011753428311494578
        },
        "100": {
            "xsec_pb": 0.26919321,
            "unc_up_pb": 0.018546568068946504,
            "unc_down_pb": -0.015399225189783653,
            "unc_scale_up_pb": 0.016638249999999966,
            "unc_scale_down_pb": -0.013038109999999992,
            "unc_pdf_up_pb": 0.008194133515727424,
            "unc_pdf_down_pb": -0.008194133515727424
        },
        "110": {
            "xsec_pb": 0.1875123,
            "unc_up_pb": 0.012754762916968691,
            "unc_down_pb": -0.010665583059879073,
            "unc_scale_up_pb": 0.011300250000000012,
            "unc_scale_down_pb": -0.00887504,
            "unc_pdf_up_pb": 0.005915093152738971,
            "unc_pdf_down_pb": -0.005915093152738971
        },
        "120": {
            "xsec_pb": 0.13480918,
            "unc_up_pb": 0.009056210938686872,
            "unc_down_pb": -0.007622829677363397,
            "unc_scale_up_pb": 0.007930280000000026,
            "unc_scale_down_pb": -0.0062435500000000005,
            "unc_pdf_up_pb": 0.004373284313601367,
            "unc_pdf_down_pb": -0.004373284313601367
        },
        "130": {
            "xsec_pb": 0.099463128,
            "unc_up_pb": 0.006633932653282453,
            "unc_down_pb": -0.005629558847618442,
            "unc_scale_up_pb": 0.005718632000000001,
            "unc_scale_down_pb": -0.004515043999999996,
            "unc_pdf_up_pb": 0.00336248576158519,
            "unc_pdf_down_pb": -0.00336248576158519
        },
        "140": {
            "xsec_pb": 0.074960098,
            "unc_up_pb": 0.004960814565922423,
            "unc_down_pb": -0.004238796432135922,
            "unc_scale_up_pb": 0.004221127999999984,
            "unc_scale_down_pb": -0.0033429980000000067,
            "unc_pdf_up_pb": 0.002606100451840679,
            "unc_pdf_down_pb": -0.002606100451840679
        },
        "150": {
            "xsec_pb": 0.057542437,
            "unc_up_pb": 0.0037985926033959295,
            "unc_down_pb": -0.0032695785562665792,
            "unc_scale_up_pb": 0.0031801489999999932,
            "unc_scale_down_pb": -0.0025247150000000107,
            "unc_pdf_up_pb": 0.002077488412572558,
            "unc_pdf_down_pb": -0.002077488412572558
        },
        "160": {
            "xsec_pb": 0.044859375,
            "unc_up_pb": 0.002953480075576231,
            "unc_down_pb": -0.0025595204965275895,
            "unc_scale_up_pb": 0.0024349249999999906,
            "unc_scale_down_pb": -0.0019382880000000102,
            "unc_pdf_up_pb": 0.00167158152693813,
            "unc_pdf_down_pb": -0.00167158152693813
        },
        "170": {
            "xsec_pb": 0.035449716,
            "unc_up_pb": 0.002336333492728772,
            "unc_down_pb": -0.002039341253179854,
            "unc_scale_up_pb": 0.001892267000000003,
            "unc_scale_down_pb": -0.0015103419999999979,
            "unc_pdf_up_pb": 0.0013703210536064887,
            "unc_pdf_down_pb": -0.0013703210536064887
        },
        "180": {
            "xsec_pb": 0.028350598,
            "unc_up_pb": 0.0018779921940012632,
            "unc_down_pb": -0.0016571746967579144,
            "unc_scale_up_pb": 0.0014908459999999988,
            "unc_scale_down_pb": -0.0012008310000000012,
            "unc_pdf_up_pb": 0.0011420301594151014,
            "unc_pdf_down_pb": -0.0011420301594151014
        },
        "190": {
            "xsec_pb": 0.022908735,
            "unc_up_pb": 0.0015183498628070548,
            "unc_down_pb": -0.0013357161898544152,
            "unc_scale_up_pb": 0.0011940240000000036,
            "unc_scale_down_pb": -0.000951022999999997,
            "unc_pdf_up_pb": 0.00093791950257482,
            "unc_pdf_down_pb": -0.00093791950257482
        },
        "200": {
            "xsec_pb": 0.018693243,
            "unc_up_pb": 0.0012537666533522797,
            "unc_down_pb": -0.001101782016590927,
            "unc_scale_up_pb": 0.0009701879999999986,
            "unc_scale_down_pb": -0.0007637130000000009,
            "unc_pdf_up_pb": 0.0007941448644385814,
            "unc_pdf_down_pb": -0.0007941448644385814
        },
        "210": {
            "xsec_pb": 0.01538433,
            "unc_up_pb": 0.0010499820226358334,
            "unc_down_pb": -0.000915859969383663,
            "unc_scale_up_pb": 0.0008042419999999984,
            "unc_scale_down_pb": -0.0006189850000000007,
            "unc_pdf_up_pb": 0.000675023742763498,
            "unc_pdf_down_pb": -0.000675023742763498
        },
        "220": {
            "xsec_pb": 0.012753852,
            "unc_up_pb": 0.0008845003753060187,
            "unc_down_pb": -0.0007641006255117744,
            "unc_scale_up_pb": 0.0006754029999999989,
            "unc_scale_down_pb": -0.0005076200000000012,
            "unc_pdf_up_pb": 0.0005711144381886054,
            "unc_pdf_down_pb": -0.0005711144381886054
        },
        "230": {
            "xsec_pb": 0.010651268,
            "unc_up_pb": 0.000746680800388339,
            "unc_down_pb": -0.0006438133440909507,
            "unc_scale_up_pb": 0.0005658079999999975,
            "unc_scale_down_pb": -0.00042083500000000135,
            "unc_pdf_up_pb": 0.0004872304637484939,
            "unc_pdf_down_pb": -0.0004872304637484939
        },
        "240": {
            "xsec_pb": 0.0089514266,
            "unc_up_pb": 0.000639062224464894,
            "unc_down_pb": -0.000550417430679344,
            "unc_scale_up_pb": 0.00047730710000000107,
            "unc_scale_down_pb": -0.0003498297999999997,
            "unc_pdf_up_pb": 0.0004249452423873095,
            "unc_pdf_down_pb": -0.0004249452423873095
        },
        "250": {
            "xsec_pb": 0.0075663676,
            "unc_up_pb": 0.0005485384457655134,
            "unc_down_pb": -0.0004713237657884414,
            "unc_scale_up_pb": 0.00040591169999999906,
            "unc_scale_down_pb": -0.00029328479999999983,
            "unc_pdf_up_pb": 0.0003689581524861007,
            "unc_pdf_down_pb": -0.0003689581524861007
        },
        "260": {
            "xsec_pb": 0.0064300009,
            "unc_up_pb": 0.000473172039172142,
            "unc_down_pb": -0.00040560708417365285,
            "unc_scale_up_pb": 0.00034681239999999986,
            "unc_scale_down_pb": -0.0002467877000000003,
            "unc_pdf_up_pb": 0.0003218896361496636,
            "unc_pdf_down_pb": -0.0003218896361496636
        },
        "270": {
            "xsec_pb": 0.0054924955,
            "unc_up_pb": 0.0004108738178170805,
            "unc_down_pb": -0.000352902073646192,
            "unc_scale_up_pb": 0.00029691080000000076,
            "unc_scale_down_pb": -0.00020947219999999924,
            "unc_pdf_up_pb": 0.0002840092797972328,
            "unc_pdf_down_pb": -0.0002840092797972328
        },
        "280": {
            "xsec_pb": 0.004712073,
            "unc_up_pb": 0.00035681798317497096,
            "unc_down_pb": -0.0003066351922326652,
            "unc_scale_up_pb": 0.0002550874999999995,
            "unc_scale_down_pb": -0.00017825739999999994,
            "unc_pdf_up_pb": 0.000249498377671687,
            "unc_pdf_down_pb": -0.000249498377671687
        },
        "290": {
            "xsec_pb": 0.00406071,
            "unc_up_pb": 0.0003112953531399927,
            "unc_down_pb": -0.00026776211436966267,
            "unc_scale_up_pb": 0.0002199671999999998,
            "unc_scale_down_pb": -0.000152241,
            "unc_pdf_up_pb": 0.00022027080562505902,
            "unc_pdf_down_pb": -0.00022027080562505902
        },
        "300": {
            "xsec_pb": 0.0035126417,
            "unc_up_pb": 0.00027356980661558984,
            "unc_down_pb": -0.00023584310643139789,
            "unc_scale_up_pb": 0.00019055630000000025,
            "unc_scale_down_pb": -0.0001307410999999998,
            "unc_pdf_up_pb": 0.00019628738019037662,
            "unc_pdf_down_pb": -0.00019628738019037662
        },
        "310": {
            "xsec_pb": 0.0030498817,
            "unc_up_pb": 0.00024038232017702961,
            "unc_down_pb": -0.00020735785318760463,
            "unc_scale_up_pb": 0.00016580989999999993,
            "unc_scale_down_pb": -0.00011272329999999979,
            "unc_pdf_up_pb": 0.00017404234230692872,
            "unc_pdf_down_pb": -0.00017404234230692872
        },
        "320": {
            "xsec_pb": 0.0026576543,
            "unc_up_pb": 0.0002123262983113702,
            "unc_down_pb": -0.00018377140281267582,
            "unc_scale_up_pb": 0.00014432840000000013,
            "unc_scale_down_pb": -9.757129999999996e-05,
            "unc_pdf_up_pb": 0.00015572979775254587,
            "unc_pdf_down_pb": -0.00015572979775254587
        },
        "330": {
            "xsec_pb": 0.0023230633,
            "unc_up_pb": 0.0001879171870866848,
            "unc_down_pb": -0.0001629078452297563,
            "unc_scale_up_pb": 0.0001263388999999998,
            "unc_scale_down_pb": -8.477980000000016e-05,
            "unc_pdf_up_pb": 0.00013910913539146944,
            "unc_pdf_down_pb": -0.00013910913539146944
        },
        "340": {
            "xsec_pb": 0.0020368567,
            "unc_up_pb": 0.00016676731513929152,
            "unc_down_pb": -0.00014497683331252483,
            "unc_scale_up_pb": 0.00011047130000000011,
            "unc_scale_down_pb": -7.355849999999978e-05,
            "unc_pdf_up_pb": 0.00012492969733044938,
            "unc_pdf_down_pb": -0.00012492969733044938
        },
        "350": {
            "xsec_pb": 0.0017911054,
            "unc_up_pb": 0.0001481601889571039,
            "unc_down_pb": -0.00012886025348172577,
            "unc_scale_up_pb": 9.728979999999981e-05,
            "unc_scale_down_pb": -6.417810000000027e-05,
            "unc_pdf_up_pb": 0.00011174138180533057,
            "unc_pdf_down_pb": -0.00011174138180533057
        },
        "360": {
            "xsec_pb": 0.0015794663,
            "unc_up_pb": 0.00013289014837720688,
            "unc_down_pb": -0.00011635967856433787,
            "unc_scale_up_pb": 8.56136000000001e-05,
            "unc_scale_down_pb": -5.665219999999988e-05,
            "unc_pdf_up_pb": 0.00010163711443540716,
            "unc_pdf_down_pb": -0.00010163711443540716
        },
        "370": {
            "xsec_pb": 0.0013962479,
            "unc_up_pb": 0.00011888257272805577,
            "unc_down_pb": -0.00010458426244139933,
            "unc_scale_up_pb": 7.56337999999997e-05,
            "unc_scale_down_pb": -5.025210000000023e-05,
            "unc_pdf_up_pb": 9.172019622744756e-05,
            "unc_pdf_down_pb": -9.172019622744756e-05
        },
        "380": {
            "xsec_pb": 0.0012373639,
            "unc_up_pb": 0.00010688543132679484,
            "unc_down_pb": -9.436782368426732e-05,
            "unc_scale_up_pb": 6.70600999999999e-05,
            "unc_scale_down_pb": -4.447300000000017e-05,
            "unc_pdf_up_pb": 8.323123462922419e-05,
            "unc_pdf_down_pb": -8.323123462922419e-05
        },
        "390": {
            "xsec_pb": 0.0010992315,
            "unc_up_pb": 9.629705134475174e-05,
            "unc_down_pb": -8.567580133651351e-05,
            "unc_scale_up_pb": 5.924649999999995e-05,
            "unc_scale_down_pb": -3.9716100000000004e-05,
            "unc_pdf_up_pb": 7.591425647033464e-05,
            "unc_pdf_down_pb": -7.591425647033464e-05
        },
        "400": {
            "xsec_pb": 0.00097852508,
            "unc_up_pb": 8.682650629488628e-05,
            "unc_down_pb": -7.770281024115926e-05,
            "unc_scale_up_pb": 5.258052000000008e-05,
            "unc_scale_down_pb": -3.5547089999999996e-05,
            "unc_pdf_up_pb": 6.909508746579246e-05,
            "unc_pdf_down_pb": -6.909508746579246e-05
        },
        "450": {
            "xsec_pb": 0.00056323545,
            "unc_up_pb": 5.379631958872625e-05,
            "unc_down_pb": -4.909860989928697e-05,
            "unc_scale_up_pb": 3.023970000000007e-05,
            "unc_scale_down_pb": -2.0762199999999975e-05,
            "unc_pdf_up_pb": 4.449274710784179e-05,
            "unc_pdf_down_pb": -4.449274710784179e-05
        },
        "500": {
            "xsec_pb": 0.00033781991,
            "unc_up_pb": 3.461921293231635e-05,
            "unc_down_pb": -3.204825293801613e-05,
            "unc_scale_up_pb": 1.807746e-05,
            "unc_scale_down_pb": -1.2465759999999996e-05,
            "unc_pdf_up_pb": 2.9524487192861792e-05,
            "unc_pdf_down_pb": -2.9524487192861792e-05
        },
        "550": {
            "xsec_pb": 0.00020953194,
            "unc_up_pb": 2.3273464673069143e-05,
            "unc_down_pb": -2.1842410420919623e-05,
            "unc_scale_up_pb": 1.116263999999999e-05,
            "unc_scale_down_pb": -7.748629999999998e-06,
            "unc_pdf_up_pb": 2.0421792921264234e-05,
            "unc_pdf_down_pb": -2.0421792921264234e-05
        },
        "600": {
            "xsec_pb": 0.00013357939,
            "unc_up_pb": 1.6139558793643392e-05,
            "unc_down_pb": -1.5291369395753047e-05,
            "unc_scale_up_pb": 7.141689999999972e-06,
            "unc_scale_down_pb": -4.9340000000000175e-06,
            "unc_pdf_up_pb": 1.4473479954640227e-05,
            "unc_pdf_down_pb": -1.4473479954640227e-05
        },
        "650": {
            "xsec_pb": 8.718018e-05,
            "unc_up_pb": 1.1482685621914136e-05,
            "unc_down_pb": -1.0992249290358597e-05,
            "unc_scale_up_pb": 4.634133000000007e-06,
            "unc_scale_down_pb": -3.233057999999986e-06,
            "unc_pdf_up_pb": 1.0506040187912137e-05,
            "unc_pdf_down_pb": -1.0506040187912137e-05
        },
        "700": {
            "xsec_pb": 5.8038352e-05,
            "unc_up_pb": 8.399396123493394e-06,
            "unc_down_pb": -8.108287982965068e-06,
            "unc_scale_up_pb": 3.0644060000000106e-06,
            "unc_scale_down_pb": -2.141275999999997e-06,
            "unc_pdf_up_pb": 7.820439316721266e-06,
            "unc_pdf_down_pb": -7.820439316721266e-06
        },
        "750": {
            "xsec_pb": 3.9298224e-05,
            "unc_up_pb": 6.270882531932263e-06,
            "unc_down_pb": -6.0905518778157745e-06,
            "unc_scale_up_pb": 2.0743469999999966e-06,
            "unc_scale_down_pb": -1.4400590000000012e-06,
            "unc_pdf_up_pb": 5.917858755739632e-06,
            "unc_pdf_down_pb": -5.917858755739632e-06
        },
        "800": {
            "xsec_pb": 2.7010612e-05,
            "unc_up_pb": 4.766463365285291e-06,
            "unc_down_pb": -4.6564052750249085e-06,
            "unc_scale_up_pb": 1.4169039999999958e-06,
            "unc_scale_down_pb": -9.851670000000034e-07,
            "unc_pdf_up_pb": 4.550995063432917e-06,
            "unc_pdf_down_pb": -4.550995063432917e-06
        },
        "850": {
            "xsec_pb": 1.8807911e-05,
            "unc_up_pb": 3.677502099757257e-06,
            "unc_down_pb": -3.6070864761862924e-06,
            "unc_scale_up_pb": 9.862929999999968e-07,
            "unc_scale_down_pb": -6.781040000000021e-07,
            "unc_pdf_up_pb": 3.542774027774004e-06,
            "unc_pdf_down_pb": -3.542774027774004e-06
        },
        "900": {
            "xsec_pb": 1.3252098e-05,
            "unc_up_pb": 2.8788787363119885e-06,
            "unc_down_pb": -2.834230360349228e-06,
            "unc_scale_up_pb": 6.915920000000001e-07,
            "unc_scale_down_pb": -4.724599999999999e-07,
            "unc_pdf_up_pb": 2.794573900244063e-06,
            "unc_pdf_down_pb": -2.794573900244063e-06
        },
        "950": {
            "xsec_pb": 9.4352369e-06,
            "unc_up_pb": 2.2783516341685585e-06,
            "unc_down_pb": -2.2503442850103057e-06,
            "unc_scale_up_pb": 4.86972199999998e-07,
            "unc_scale_down_pb": -3.3212220000000066e-07,
            "unc_pdf_up_pb": 2.2257008436323384e-06,
            "unc_pdf_down_pb": -2.2257008436323384e-06
        },
        "1000": {
            "xsec_pb": 6.7817691e-06,
            "unc_up_pb": 1.8217752130064705e-06,
            "unc_down_pb": -1.8042239330443372e-06,
            "unc_scale_up_pb": 3.4731269999999995e-07,
            "unc_scale_down_pb": -2.3871570000000056e-07,
            "unc_pdf_up_pb": 1.7883620481165107e-06,
            "unc_pdf_down_pb": -1.7883620481165124e-06
        }
    }
}