{
    "initial state": "pp",
    "order": "NNLOapprox+NNLL",
    "source": "hepi-0.2.17.12",
    "contact": "Alexander Puck Neuwirth <alexander@neuwirth-informatik.de>",
    "tool": "Resummino-resummino 3.1.2-dev",
    "process_latex": "$\\tilde{e}_{L}^{+}\\tilde{\\nu}_{eL}$",
    "comment": "0.0.0",
    "reference": "?",
    "Ecom [GeV]": "13600",
    "process_id": "pp_13600_-1000011_1000012",
    "PDF set": "PDF4LHC21_40",
    "parameters": [
        [
            "mass_-1000011_1000012"
        ]
    ],
    "data": {
        "50": {
            "xsec_pb": 13.9516,
            "unc_up_pb": 1.0968690446326195,
            "unc_down_pb": -1.0349548448049648,
            "unc_scale_up_pb": 1.0365730000000015,
            "unc_scale_down_pb": -0.9708209999999982,
            "unc_pdf_up_pb": 0.3586615629591109,
            "unc_pdf_down_pb": -0.3586615629591109
        },
        "60": {
            "xsec_pb": 6.0666054,
            "unc_up_pb": 0.460866238824803,
            "unc_down_pb": -0.37152470822760914,
            "unc_scale_up_pb": 0.43162539999999927,
            "unc_scale_down_pb": -0.3345645000000004,
            "unc_pdf_up_pb": 0.16154629108512625,
            "unc_pdf_down_pb": -0.16154629108512625
        },
        "70": {
            "xsec_pb": 3.2717199,
            "unc_up_pb": 0.24092204539414386,
            "unc_down_pb": -0.19621646093541045,
            "unc_scale_up_pb": 0.2228627999999997,
            "unc_scale_down_pb": -0.17356640000000034,
            "unc_pdf_up_pb": 0.09151832785326472,
            "unc_pdf_down_pb": -0.09151832785326472
        },
        "80": {
            "xsec_pb": 1.9740351,
            "unc_up_pb": 0.14182312396712662,
            "unc_down_pb": -0.11654605456571623,
            "unc_scale_up_pb": 0.12977360000000004,
            "unc_scale_down_pb": -0.10153999999999996,
            "unc_pdf_up_pb": 0.05720674116601035,
            "unc_pdf_down_pb": -0.057206741166010794
        },
        "90": {
            "xsec_pb": 1.2798244,
            "unc_up_pb": 0.09019084262737168,
            "unc_down_pb": -0.07461341910531519,
            "unc_scale_up_pb": 0.08163469999999995,
            "unc_scale_down_pb": -0.06400780000000017,
            "unc_pdf_up_pb": 0.03834271573252687,
            "unc_pdf_down_pb": -0.03834271573252687
        },
        "100": {
            "xsec_pb": 0.8737589,
            "unc_up_pb": 0.06053465344410294,
            "unc_down_pb": -0.05040112666094412,
            "unc_scale_up_pb": 0.05419810000000008,
            "unc_scale_down_pb": -0.042582430000000004,
            "unc_pdf_up_pb": 0.0269631271181151,
            "unc_pdf_down_pb": -0.0269631271181151
        },
        "110": {
            "xsec_pb": 0.6200433,
            "unc_up_pb": 0.04235467806136173,
            "unc_down_pb": -0.03556160577717482,
            "unc_scale_up_pb": 0.03742790000000007,
            "unc_scale_down_pb": -0.029522139999999975,
            "unc_pdf_up_pb": 0.019826019652759194,
            "unc_pdf_down_pb": -0.019826019652759194
        },
        "120": {
            "xsec_pb": 0.45387166,
            "unc_up_pb": 0.030595152975325682,
            "unc_down_pb": -0.02588570467855146,
            "unc_scale_up_pb": 0.026704249999999985,
            "unc_scale_down_pb": -0.021145289999999983,
            "unc_pdf_up_pb": 0.014931390341193316,
            "unc_pdf_down_pb": -0.014931390341193316
        },
        "130": {
            "xsec_pb": 0.34054141,
            "unc_up_pb": 0.022765112730909632,
            "unc_down_pb": -0.01939538156551256,
            "unc_scale_up_pb": 0.01961196000000001,
            "unc_scale_down_pb": -0.015574319999999947,
            "unc_pdf_up_pb": 0.011559471554073088,
            "unc_pdf_down_pb": -0.011559471554073088
        },
        "140": {
            "xsec_pb": 0.26088157,
            "unc_up_pb": 0.017306162103629195,
            "unc_down_pb": -0.014829826542903067,
            "unc_scale_up_pb": 0.014730609999999991,
            "unc_scale_down_pb": -0.011722259999999998,
            "unc_pdf_up_pb": 0.009083632301287408,
            "unc_pdf_down_pb": -0.009083632301287408
        },
        "150": {
            "xsec_pb": 0.20338443,
            "unc_up_pb": 0.013442886148439434,
            "unc_down_pb": -0.01158203805691834,
            "unc_scale_up_pb": 0.011281980000000011,
            "unc_scale_down_pb": -0.008984179999999994,
            "unc_pdf_up_pb": 0.007309453829083588,
            "unc_pdf_down_pb": -0.007309453829083588
        },
        "160": {
            "xsec_pb": 0.16099028,
            "unc_up_pb": 0.010585046839596199,
            "unc_down_pb": -0.009204167082036571,
            "unc_scale_up_pb": 0.008782250000000005,
            "unc_scale_down_pb": -0.007057009999999989,
            "unc_pdf_up_pb": 0.00590891712024679,
            "unc_pdf_down_pb": -0.00590891712024679
        },
        "170": {
            "xsec_pb": 0.12909729,
            "unc_up_pb": 0.008483005751775645,
            "unc_down_pb": -0.0074200543998112645,
            "unc_scale_up_pb": 0.006932210000000001,
            "unc_scale_down_pb": -0.005581339999999997,
            "unc_pdf_up_pb": 0.004889361011477736,
            "unc_pdf_down_pb": -0.004889361011477736
        },
        "180": {
            "xsec_pb": 0.10465951,
            "unc_up_pb": 0.006912289500649212,
            "unc_down_pb": -0.006015109788257013,
            "unc_scale_up_pb": 0.005574429999999998,
            "unc_scale_down_pb": -0.004413170000000001,
            "unc_pdf_up_pb": 0.004087233332694053,
            "unc_pdf_down_pb": -0.004087233332694053
        },
        "190": {
            "xsec_pb": 0.08575469,
            "unc_up_pb": 0.005668139263179769,
            "unc_down_pb": -0.004954235576682727,
            "unc_scale_up_pb": 0.004508333999999996,
            "unc_scale_down_pb": -0.003569554999999995,
            "unc_pdf_up_pb": 0.0034355097512951387,
            "unc_pdf_down_pb": -0.0034355097512951387
        },
        "200": {
            "xsec_pb": 0.070908322,
            "unc_up_pb": 0.004733087404704241,
            "unc_down_pb": -0.004108328275440389,
            "unc_scale_up_pb": 0.0037459260000000175,
            "unc_scale_down_pb": -0.002916882999999988,
            "unc_pdf_up_pb": 0.002893121978606147,
            "unc_pdf_down_pb": -0.002893121978606147
        },
        "210": {
            "xsec_pb": 0.059117794,
            "unc_up_pb": 0.004015509055398612,
            "unc_down_pb": -0.0034726792204451086,
            "unc_scale_up_pb": 0.003142948999999999,
            "unc_scale_down_pb": -0.002411082000000002,
            "unc_pdf_up_pb": 0.0024992367949810694,
            "unc_pdf_down_pb": -0.0024992367949810694
        },
        "220": {
            "xsec_pb": 0.049634167,
            "unc_up_pb": 0.003424700226625432,
            "unc_down_pb": -0.0029376028259993385,
            "unc_scale_up_pb": 0.0026659349999999978,
            "unc_scale_down_pb": -0.002002036000000002,
            "unc_pdf_up_pb": 0.0021497353832561103,
            "unc_pdf_down_pb": -0.0021497353832561103
        },
        "230": {
            "xsec_pb": 0.041963134,
            "unc_up_pb": 0.0029077357851927258,
            "unc_down_pb": -0.0024876649395698955,
            "unc_scale_up_pb": 0.0022526549999999958,
            "unc_scale_down_pb": -0.0016757100000000004,
            "unc_pdf_up_pb": 0.0018386062241451614,
            "unc_pdf_down_pb": -0.0018386062241451614
        },
        "240": {
            "xsec_pb": 0.035685874,
            "unc_up_pb": 0.0025079874494191683,
            "unc_down_pb": -0.002137667247986929,
            "unc_scale_up_pb": 0.0019280570000000004,
            "unc_scale_down_pb": -0.0014131609999999996,
            "unc_pdf_up_pb": 0.0016039318100203117,
            "unc_pdf_down_pb": -0.0016039318100203117
        },
        "250": {
            "xsec_pb": 0.030519015,
            "unc_up_pb": 0.002169682888126364,
            "unc_down_pb": -0.0018485129683644,
            "unc_scale_up_pb": 0.0016524790000000036,
            "unc_scale_down_pb": -0.0012000679999999968,
            "unc_pdf_up_pb": 0.0014060003519158033,
            "unc_pdf_down_pb": -0.0014060003519158033
        },
        "260": {
            "xsec_pb": 0.026234505,
            "unc_up_pb": 0.0018786099675295992,
            "unc_down_pb": -0.001600574386511467,
            "unc_scale_up_pb": 0.0014188969999999988,
            "unc_scale_down_pb": -0.0010227080000000006,
            "unc_pdf_up_pb": 0.0012312216345940973,
            "unc_pdf_down_pb": -0.0012312216345940973
        },
        "270": {
            "xsec_pb": 0.022648964,
            "unc_up_pb": 0.0016445025681432026,
            "unc_down_pb": -0.0013948275558701125,
            "unc_scale_up_pb": 0.0012348480000000002,
            "unc_scale_down_pb": -0.000875217000000001,
            "unc_pdf_up_pb": 0.001086065888206415,
            "unc_pdf_down_pb": -0.001086065888206415
        },
        "280": {
            "xsec_pb": 0.019646887,
            "unc_up_pb": 0.0014426332181999867,
            "unc_down_pb": -0.0012195232738669037,
            "unc_scale_up_pb": 0.0010766240000000052,
            "unc_scale_down_pb": -0.0007517749999999962,
            "unc_pdf_up_pb": 0.0009602454711572708,
            "unc_pdf_down_pb": -0.0009602454711572708
        },
        "290": {
            "xsec_pb": 0.017107585,
            "unc_up_pb": 0.0012689262919209983,
            "unc_down_pb": -0.0010733538044318679,
            "unc_scale_up_pb": 0.0009379429999999984,
            "unc_scale_down_pb": -0.0006493470000000032,
            "unc_pdf_up_pb": 0.0008546559910744019,
            "unc_pdf_down_pb": -0.0008546559910744019
        },
        "300": {
            "xsec_pb": 0.014952728,
            "unc_up_pb": 0.0011213239707958088,
            "unc_down_pb": -0.0009475723614881734,
            "unc_scale_up_pb": 0.0008225409999999996,
            "unc_scale_down_pb": -0.0005631160000000024,
            "unc_pdf_up_pb": 0.0007620982553452508,
            "unc_pdf_down_pb": -0.0007620982553452508
        },
        "310": {
            "xsec_pb": 0.01311619,
            "unc_up_pb": 0.0009912876175111884,
            "unc_down_pb": -0.000839020851728968,
            "unc_scale_up_pb": 0.0007204219999999983,
            "unc_scale_down_pb": -0.0004902170000000011,
            "unc_pdf_up_pb": 0.0006809135646666217,
            "unc_pdf_down_pb": -0.0006809135646666217
        },
        "320": {
            "xsec_pb": 0.011541815,
            "unc_up_pb": 0.0008817802169805221,
            "unc_down_pb": -0.0007493062231205753,
            "unc_scale_up_pb": 0.0006337739999999993,
            "unc_scale_down_pb": -0.000430805000000002,
            "unc_pdf_up_pb": 0.0006130798218684241,
            "unc_pdf_down_pb": -0.0006130798218684241
        },
        "330": {
            "xsec_pb": 0.010189282,
            "unc_up_pb": 0.0007837654760652871,
            "unc_down_pb": -0.0006692205415989934,
            "unc_scale_up_pb": 0.0005597990000000023,
            "unc_scale_down_pb": -0.00038333109999999764,
            "unc_pdf_up_pb": 0.0005485557410791021,
            "unc_pdf_down_pb": -0.0005485557410791021
        },
        "340": {
            "xsec_pb": 0.0090188337,
            "unc_up_pb": 0.000701397752505818,
            "unc_down_pb": -0.0005996098317926604,
            "unc_scale_up_pb": 0.0004970201999999991,
            "unc_scale_down_pb": -0.0003385294999999995,
            "unc_pdf_up_pb": 0.0004949037563124502,
            "unc_pdf_down_pb": -0.0004949037563124502
        },
        "350": {
            "xsec_pb": 0.008007226,
            "unc_up_pb": 0.000625777221236918,
            "unc_down_pb": -0.0005391965238044354,
            "unc_scale_up_pb": 0.00043911890000000123,
            "unc_scale_down_pb": -0.0003032509999999983,
            "unc_pdf_up_pb": 0.0004458382243390398,
            "unc_pdf_down_pb": -0.0004458382243390398
        },
        "360": {
            "xsec_pb": 0.0071254381,
            "unc_up_pb": 0.0005636489848920069,
            "unc_down_pb": -0.0004879092734442641,
            "unc_scale_up_pb": 0.0003914576999999998,
            "unc_scale_down_pb": -0.0002712829000000006,
            "unc_pdf_up_pb": 0.0004055379726739526,
            "unc_pdf_down_pb": -0.0004055379726739526
        },
        "370": {
            "xsec_pb": 0.0063557272,
            "unc_up_pb": 0.000506571479265081,
            "unc_down_pb": -0.0004395408790897748,
            "unc_scale_up_pb": 0.00034876859999999907,
            "unc_scale_down_pb": -0.00024129040000000048,
            "unc_pdf_up_pb": 0.0003673896123447863,
            "unc_pdf_down_pb": -0.0003673896123447863
        },
        "380": {
            "xsec_pb": 0.00568319,
            "unc_up_pb": 0.00045561846343144787,
            "unc_down_pb": -0.00039815225815463415,
            "unc_scale_up_pb": 0.00031016869999999936,
            "unc_scale_down_pb": -0.00021712130000000034,
            "unc_pdf_up_pb": 0.00033374175908918585,
            "unc_pdf_down_pb": -0.00033374175908918585
        },
        "390": {
            "xsec_pb": 0.0050920678,
            "unc_up_pb": 0.00041130240671654136,
            "unc_down_pb": -0.0003608521773233177,
            "unc_scale_up_pb": 0.0002775924999999994,
            "unc_scale_down_pb": -0.00019519790000000056,
            "unc_pdf_up_pb": 0.00030349970957905246,
            "unc_pdf_down_pb": -0.00030349970957905246
        },
        "400": {
            "xsec_pb": 0.0045714126,
            "unc_up_pb": 0.0003734306902121072,
            "unc_down_pb": -0.00032844992569420854,
            "unc_scale_up_pb": 0.00024983350000000026,
            "unc_scale_down_pb": -0.00017562929999999973,
            "unc_pdf_up_pb": 0.0002775494598626359,
            "unc_pdf_down_pb": -0.0002775494598626359
        },
        "450": {
            "xsec_pb": 0.0027391356,
            "unc_up_pb": 0.00023393264679930575,
            "unc_down_pb": -0.00020913355103000284,
            "unc_scale_up_pb": 0.00014942940000000032,
            "unc_scale_down_pb": -0.00010649649999999971,
            "unc_pdf_up_pb": 0.00017998704857341474,
            "unc_pdf_down_pb": -0.00017998704857341474
        },
        "500": {
            "xsec_pb": 0.0017046731,
            "unc_up_pb": 0.00015260443655656754,
            "unc_down_pb": -0.00013819583610061257,
            "unc_scale_up_pb": 9.279310000000012e-05,
            "unc_scale_down_pb": -6.648709999999987e-05,
            "unc_pdf_up_pb": 0.00012115095810243271,
            "unc_pdf_down_pb": -0.00012115095810243271
        },
        "550": {
            "xsec_pb": 0.0010935419,
            "unc_up_pb": 0.00010271981343199651,
            "unc_down_pb": -9.403297919615341e-05,
            "unc_scale_up_pb": 5.9484000000000056e-05,
            "unc_scale_down_pb": -4.276900000000001e-05,
            "unc_pdf_up_pb": 8.374373896300662e-05,
            "unc_pdf_down_pb": -8.374373896300662e-05
        },
        "600": {
            "xsec_pb": 0.00071912409,
            "unc_up_pb": 7.11850452801092e-05,
            "unc_down_pb": -6.58930576910549e-05,
            "unc_scale_up_pb": 3.897271e-05,
            "unc_scale_down_pb": -2.816835999999999e-05,
            "unc_pdf_up_pb": 5.95687715735946e-05,
            "unc_pdf_down_pb": -5.95687715735946e-05
        },
        "650": {
            "xsec_pb": 0.00048275958,
            "unc_up_pb": 5.047916742928744e-05,
            "unc_down_pb": -4.719785311136663e-05,
            "unc_scale_up_pb": 2.6039999999999988e-05,
            "unc_scale_down_pb": -1.890958999999995e-05,
            "unc_pdf_up_pb": 4.324424521660701e-05,
            "unc_pdf_down_pb": -4.324424521660701e-05
        },
        "700": {
            "xsec_pb": 0.00032977903,
            "unc_up_pb": 3.662557101725757e-05,
            "unc_down_pb": -3.454947631738826e-05,
            "unc_scale_up_pb": 1.7747879999999985e-05,
            "unc_scale_down_pb": -1.2931400000000016e-05,
            "unc_pdf_up_pb": 3.2038183591548614e-05,
            "unc_pdf_down_pb": -3.2038183591548614e-05
        },
        "750": {
            "xsec_pb": 0.00022858888,
            "unc_up_pb": 2.7120119753699078e-05,
            "unc_down_pb": -2.578562482387e-05,
            "unc_scale_up_pb": 1.226875999999997e-05,
            "unc_scale_down_pb": -8.939800000000033e-06,
            "unc_pdf_up_pb": 2.4186327201900247e-05,
            "unc_pdf_down_pb": -2.4186327201900247e-05
        },
        "800": {
            "xsec_pb": 0.00016047139,
            "unc_up_pb": 2.04544262672068e-05,
            "unc_down_pb": -1.95630221076652e-05,
            "unc_scale_up_pb": 8.624400000000005e-06,
            "unc_scale_down_pb": -6.221619999999996e-06,
            "unc_pdf_up_pb": 1.854732537485118e-05,
            "unc_pdf_down_pb": -1.854732537485118e-05
        },
        "850": {
            "xsec_pb": 0.00011390904,
            "unc_up_pb": 1.5684725863096586e-05,
            "unc_down_pb": -1.5093589202853343e-05,
            "unc_scale_up_pb": 6.107959999999994e-06,
            "unc_scale_down_pb": -4.3718400000000005e-06,
            "unc_pdf_up_pb": 1.4446572259151683e-05,
            "unc_pdf_down_pb": -1.4446572259151683e-05
        },
        "900": {
            "xsec_pb": 8.1653312e-05,
            "unc_up_pb": 1.22255089015645e-05,
            "unc_down_pb": -1.1841089329669666e-05,
            "unc_scale_up_pb": 4.358171000000009e-06,
            "unc_scale_down_pb": -3.1212149999999806e-06,
            "unc_pdf_up_pb": 1.14223208428494e-05,
            "unc_pdf_down_pb": -1.14223208428494e-05
        },
        "950": {
            "xsec_pb": 5.9031644e-05,
            "unc_up_pb": 9.662373938491293e-06,
            "unc_down_pb": -9.411124590986754e-06,
            "unc_scale_up_pb": 3.1290840000000066e-06,
            "unc_scale_down_pb": -2.2358360000000017e-06,
            "unc_pdf_up_pb": 9.14167946540348e-06,
            "unc_pdf_down_pb": -9.14167946540348e-06
        },
        "1000": {
            "xsec_pb": 4.3000439e-05,
            "unc_up_pb": 7.749363418350297e-06,
            "unc_down_pb": -7.582134181274483e-06,
            "unc_scale_up_pb": 2.2760160000000037e-06,
            "unc_scale_down_pb": -1.6175209999999967e-06,
            "unc_pdf_up_pb": 7.407589659086808e-06,
            "unc_pdf_down_pb": -7.407589659086808e-06
        }
    }
}